zc.intid-2.1.0-py3.9-nspkg.pth
zc/intid/__init__.py
zc/intid/configure.zcml
zc/intid/interfaces.py
zc/intid/subscribers.py
zc/intid/subscribers.zcml
zc/intid/utility.py
zc/intid/zope-intid.zcml
zc/intid/tests/__init__.py
zc/intid/tests/test_subscribers.py
zc/intid/tests/test_utility.py
zc/intid/tests/test_zope_zcml.py
zc.intid-2.1.0.dist-info/LICENSE.txt
zc.intid-2.1.0.dist-info/METADATA
zc.intid-2.1.0.dist-info/WHEEL
zc.intid-2.1.0.dist-info/namespace_packages.txt
zc.intid-2.1.0.dist-info/top_level.txt
zc.intid-2.1.0.dist-info/RECORD
